{
  "domain_contexts": {},
  "agent_memories": {
    "StudentBAE": {
      "agent_name": "StudentBAE",
      "memory_data": {
        "current_schema": {
          "entity": "Student",
          "attributes": [
            "id: int",
            "name: str",
            "email: str"
          ],
          "context": "academic",
          "generated_at": "2025-07-03T16:39:51.646190",
          "business_rules": [
            "Registration number must be unique within institution",
            "Email must be valid and unique",
            "Age must be positive and reasonable for students (typically 16-65)",
            "GPA must be within valid range (0.0-4.0 or institutional scale)",
            "Student must be enrolled in at least one course",
            "Birth date must be consistent with declared age"
          ],
          "is_evolution": false,
          "interpretation": {
            "entity": "Student",
            "domain": "academic",
            "attributes": [
              "id: int",
              "name: str",
              "email: str"
            ],
            "extracted_attributes": [
              "id: int",
              "name: str",
              "email: str"
            ],
            "is_evolution": false,
            "request_type": "generation",
            "business_context": "Create a student management system with name and email",
            "semantic_coherence": true,
            "domain_knowledge_preserved": true,
            "interpreted_intent": "create_student_management_system",
            "domain_operations": [
              "create_entity",
              "setup_crud"
            ],
            "business_vocabulary": [
              "discente",
              "Academic",
              "aluno",
              "student",
              "Id",
              "Student",
              "estudante",
              "Learning",
              "Name",
              "Entity"
            ],
            "entity_focus": "Student",
            "swea_coordination": [
              {
                "swea_agent": "TechLeadSWEA",
                "task_type": "coordinate_system_generation",
                "payload": {
                  "entity": "Student",
                  "attributes": [
                    "id: int",
                    "name: str",
                    "email: str"
                  ],
                  "context": "Create a student management system with name and email",
                  "is_evolution": false,
                  "business_requirements": {
                    "domain_focus": true,
                    "semantic_coherence": true,
                    "quality_gates": true,
                    "technical_governance": true
                  }
                }
              },
              {
                "swea_agent": "DatabaseSWEA",
                "task_type": "setup_database",
                "payload": {
                  "entity": "Student",
                  "attributes": [
                    "id: int",
                    "name: str",
                    "email: str"
                  ],
                  "context": "Create a student management system with name and email",
                  "preserve_data": false,
                  "business_rules": true
                }
              },
              {
                "swea_agent": "BackendSWEA",
                "task_type": "generate_model",
                "payload": {
                  "entity": "Student",
                  "attributes": [
                    "id: int",
                    "name: str",
                    "email: str"
                  ],
                  "context": "Create a student management system with name and email",
                  "business_vocabulary": true,
                  "domain_focus": true,
                  "semantic_coherence": true
                }
              },
              {
                "swea_agent": "BackendSWEA",
                "task_type": "generate_api",
                "payload": {
                  "entity": "Student",
                  "attributes": [
                    "id: int",
                    "name: str",
                    "email: str"
                  ],
                  "context": "Create a student management system with name and email",
                  "crud_operations": true,
                  "business_vocabulary": true,
                  "domain_focus": true,
                  "semantic_coherence": true
                }
              },
              {
                "swea_agent": "FrontendSWEA",
                "task_type": "generate_ui",
                "payload": {
                  "entity": "Student",
                  "attributes": [
                    "id: int",
                    "name: str",
                    "email: str"
                  ],
                  "context": "Create a student management system with name and email",
                  "ui_framework": "streamlit",
                  "features": [
                    "crud_operations",
                    "data_visualization",
                    "user_friendly"
                  ]
                }
              },
              {
                "swea_agent": "TechLeadSWEA",
                "task_type": "review_and_approve",
                "payload": {
                  "entity": "Student",
                  "context": "Create a student management system with name and email",
                  "system_components": [
                    "database",
                    "backend",
                    "frontend"
                  ],
                  "phase": "phase_1_complete",
                  "final_review": true
                }
              }
            ]
          }
        }
      },
      "timestamp": "2025-07-02T14:58:55.483440"
    },
    "CourseBAE": {
      "agent_name": "CourseBAE",
      "memory_data": {
        "current_schema": {
          "entity": "Course",
          "attributes": [
            "id: int",
            "name: str",
            "course: str"
          ],
          "context": "academic",
          "generated_at": "2025-07-03T16:37:13.811181",
          "business_rules": [
            "Course code must be unique within institution",
            "Credits must be positive integer",
            "Prerequisites must reference existing courses",
            "Duration must be specified in hours or weeks",
            "Course must be assigned to a valid department",
            "Level must be appropriate (undergraduate, graduate, etc.)"
          ],
          "is_evolution": false,
          "interpretation": {
            "entity": "Course",
            "domain": "academic",
            "attributes": [
              "id: int",
              "name: str",
              "course: str"
            ],
            "extracted_attributes": [
              "id: int",
              "name: str",
              "course: str"
            ],
            "is_evolution": false,
            "request_type": "generation",
            "business_context": "Create a course entity with a name",
            "semantic_coherence": true,
            "domain_knowledge_preserved": true,
            "interpreted_intent": "create_course_management_system",
            "domain_operations": [
              "create_entity",
              "setup_crud"
            ],
            "business_vocabulary": [
              "Entity",
              "Id",
              "subject",
              "Academic",
              "course",
              "Course",
              "curso",
              "Learning",
              "disciplina",
              "mat\u00e9ria"
            ],
            "entity_focus": "Course",
            "swea_coordination": [
              {
                "swea_agent": "TechLeadSWEA",
                "task_type": "coordinate_system_generation",
                "payload": {
                  "entity": "Course",
                  "attributes": [
                    "id: int",
                    "name: str",
                    "course: str"
                  ],
                  "context": "Create a course entity with a name",
                  "is_evolution": false,
                  "business_requirements": {
                    "domain_focus": true,
                    "semantic_coherence": true,
                    "quality_gates": true,
                    "technical_governance": true
                  }
                }
              },
              {
                "swea_agent": "DatabaseSWEA",
                "task_type": "setup_database",
                "payload": {
                  "entity": "Course",
                  "attributes": [
                    "id: int",
                    "name: str",
                    "course: str"
                  ],
                  "context": "Create a course entity with a name",
                  "preserve_data": false,
                  "business_rules": true
                }
              },
              {
                "swea_agent": "BackendSWEA",
                "task_type": "generate_model",
                "payload": {
                  "entity": "Course",
                  "attributes": [
                    "id: int",
                    "name: str",
                    "course: str"
                  ],
                  "context": "Create a course entity with a name",
                  "business_vocabulary": true,
                  "domain_focus": true,
                  "semantic_coherence": true
                }
              },
              {
                "swea_agent": "BackendSWEA",
                "task_type": "generate_api",
                "payload": {
                  "entity": "Course",
                  "attributes": [
                    "id: int",
                    "name: str",
                    "course: str"
                  ],
                  "context": "Create a course entity with a name",
                  "crud_operations": true,
                  "business_vocabulary": true,
                  "domain_focus": true,
                  "semantic_coherence": true
                }
              },
              {
                "swea_agent": "FrontendSWEA",
                "task_type": "generate_ui",
                "payload": {
                  "entity": "Course",
                  "attributes": [
                    "id: int",
                    "name: str",
                    "course: str"
                  ],
                  "context": "Create a course entity with a name",
                  "ui_framework": "streamlit",
                  "features": [
                    "crud_operations",
                    "data_visualization",
                    "user_friendly"
                  ]
                }
              },
              {
                "swea_agent": "TechLeadSWEA",
                "task_type": "review_and_approve",
                "payload": {
                  "entity": "Course",
                  "context": "Create a course entity with a name",
                  "system_components": [
                    "database",
                    "backend",
                    "frontend"
                  ],
                  "phase": "phase_1_complete",
                  "final_review": true
                }
              }
            ]
          }
        }
      },
      "timestamp": "2025-07-02T15:01:24.926245"
    }
  },
  "agents": {
    "StudentBAE": {
      "memory": {
        "current_schema": {
          "entity": "Student",
          "attributes": [
            "id: int",
            "name: str",
            "email: str"
          ],
          "context": "academic",
          "generated_at": "2025-07-03T16:39:51.646190",
          "business_rules": [
            "Registration number must be unique within institution",
            "Email must be valid and unique",
            "Age must be positive and reasonable for students (typically 16-65)",
            "GPA must be within valid range (0.0-4.0 or institutional scale)",
            "Student must be enrolled in at least one course",
            "Birth date must be consistent with declared age"
          ],
          "is_evolution": false,
          "interpretation": {
            "entity": "Student",
            "domain": "academic",
            "attributes": [
              "id: int",
              "name: str",
              "email: str"
            ],
            "extracted_attributes": [
              "id: int",
              "name: str",
              "email: str"
            ],
            "is_evolution": false,
            "request_type": "generation",
            "business_context": "Create a student management system with name and email",
            "semantic_coherence": true,
            "domain_knowledge_preserved": true,
            "interpreted_intent": "create_student_management_system",
            "domain_operations": [
              "create_entity",
              "setup_crud"
            ],
            "business_vocabulary": [
              "discente",
              "Academic",
              "aluno",
              "student",
              "Id",
              "Student",
              "estudante",
              "Learning",
              "Name",
              "Entity"
            ],
            "entity_focus": "Student",
            "swea_coordination": [
              {
                "swea_agent": "TechLeadSWEA",
                "task_type": "coordinate_system_generation",
                "payload": {
                  "entity": "Student",
                  "attributes": [
                    "id: int",
                    "name: str",
                    "email: str"
                  ],
                  "context": "Create a student management system with name and email",
                  "is_evolution": false,
                  "business_requirements": {
                    "domain_focus": true,
                    "semantic_coherence": true,
                    "quality_gates": true,
                    "technical_governance": true
                  }
                }
              },
              {
                "swea_agent": "DatabaseSWEA",
                "task_type": "setup_database",
                "payload": {
                  "entity": "Student",
                  "attributes": [
                    "id: int",
                    "name: str",
                    "email: str"
                  ],
                  "context": "Create a student management system with name and email",
                  "preserve_data": false,
                  "business_rules": true
                }
              },
              {
                "swea_agent": "BackendSWEA",
                "task_type": "generate_model",
                "payload": {
                  "entity": "Student",
                  "attributes": [
                    "id: int",
                    "name: str",
                    "email: str"
                  ],
                  "context": "Create a student management system with name and email",
                  "business_vocabulary": true,
                  "domain_focus": true,
                  "semantic_coherence": true
                }
              },
              {
                "swea_agent": "BackendSWEA",
                "task_type": "generate_api",
                "payload": {
                  "entity": "Student",
                  "attributes": [
                    "id: int",
                    "name: str",
                    "email: str"
                  ],
                  "context": "Create a student management system with name and email",
                  "crud_operations": true,
                  "business_vocabulary": true,
                  "domain_focus": true,
                  "semantic_coherence": true
                }
              },
              {
                "swea_agent": "FrontendSWEA",
                "task_type": "generate_ui",
                "payload": {
                  "entity": "Student",
                  "attributes": [
                    "id: int",
                    "name: str",
                    "email: str"
                  ],
                  "context": "Create a student management system with name and email",
                  "ui_framework": "streamlit",
                  "features": [
                    "crud_operations",
                    "data_visualization",
                    "user_friendly"
                  ]
                }
              },
              {
                "swea_agent": "TechLeadSWEA",
                "task_type": "review_and_approve",
                "payload": {
                  "entity": "Student",
                  "context": "Create a student management system with name and email",
                  "system_components": [
                    "database",
                    "backend",
                    "frontend"
                  ],
                  "phase": "phase_1_complete",
                  "final_review": true
                }
              }
            ]
          }
        }
      }
    },
    "CourseBAE": {
      "memory": {
        "current_schema": {
          "entity": "Course",
          "attributes": [
            "id: int",
            "name: str",
            "course: str"
          ],
          "context": "academic",
          "generated_at": "2025-07-03T16:37:13.811181",
          "business_rules": [
            "Course code must be unique within institution",
            "Credits must be positive integer",
            "Prerequisites must reference existing courses",
            "Duration must be specified in hours or weeks",
            "Course must be assigned to a valid department",
            "Level must be appropriate (undergraduate, graduate, etc.)"
          ],
          "is_evolution": false,
          "interpretation": {
            "entity": "Course",
            "domain": "academic",
            "attributes": [
              "id: int",
              "name: str",
              "course: str"
            ],
            "extracted_attributes": [
              "id: int",
              "name: str",
              "course: str"
            ],
            "is_evolution": false,
            "request_type": "generation",
            "business_context": "Create a course entity with a name",
            "semantic_coherence": true,
            "domain_knowledge_preserved": true,
            "interpreted_intent": "create_course_management_system",
            "domain_operations": [
              "create_entity",
              "setup_crud"
            ],
            "business_vocabulary": [
              "Entity",
              "Id",
              "subject",
              "Academic",
              "course",
              "Course",
              "curso",
              "Learning",
              "disciplina",
              "mat\u00e9ria"
            ],
            "entity_focus": "Course",
            "swea_coordination": [
              {
                "swea_agent": "TechLeadSWEA",
                "task_type": "coordinate_system_generation",
                "payload": {
                  "entity": "Course",
                  "attributes": [
                    "id: int",
                    "name: str",
                    "course: str"
                  ],
                  "context": "Create a course entity with a name",
                  "is_evolution": false,
                  "business_requirements": {
                    "domain_focus": true,
                    "semantic_coherence": true,
                    "quality_gates": true,
                    "technical_governance": true
                  }
                }
              },
              {
                "swea_agent": "DatabaseSWEA",
                "task_type": "setup_database",
                "payload": {
                  "entity": "Course",
                  "attributes": [
                    "id: int",
                    "name: str",
                    "course: str"
                  ],
                  "context": "Create a course entity with a name",
                  "preserve_data": false,
                  "business_rules": true
                }
              },
              {
                "swea_agent": "BackendSWEA",
                "task_type": "generate_model",
                "payload": {
                  "entity": "Course",
                  "attributes": [
                    "id: int",
                    "name: str",
                    "course: str"
                  ],
                  "context": "Create a course entity with a name",
                  "business_vocabulary": true,
                  "domain_focus": true,
                  "semantic_coherence": true
                }
              },
              {
                "swea_agent": "BackendSWEA",
                "task_type": "generate_api",
                "payload": {
                  "entity": "Course",
                  "attributes": [
                    "id: int",
                    "name: str",
                    "course: str"
                  ],
                  "context": "Create a course entity with a name",
                  "crud_operations": true,
                  "business_vocabulary": true,
                  "domain_focus": true,
                  "semantic_coherence": true
                }
              },
              {
                "swea_agent": "FrontendSWEA",
                "task_type": "generate_ui",
                "payload": {
                  "entity": "Course",
                  "attributes": [
                    "id: int",
                    "name: str",
                    "course: str"
                  ],
                  "context": "Create a course entity with a name",
                  "ui_framework": "streamlit",
                  "features": [
                    "crud_operations",
                    "data_visualization",
                    "user_friendly"
                  ]
                }
              },
              {
                "swea_agent": "TechLeadSWEA",
                "task_type": "review_and_approve",
                "payload": {
                  "entity": "Course",
                  "context": "Create a course entity with a name",
                  "system_components": [
                    "database",
                    "backend",
                    "frontend"
                  ],
                  "phase": "phase_1_complete",
                  "final_review": true
                }
              }
            ]
          }
        }
      }
    }
  },
  "business_vocabularies": {},
  "entity_relationships": {},
  "evolution_history": [],
  "domain_knowledge": {
    "student": {
      "entity": "student",
      "knowledge": {
        "entity": "Student",
        "context": "academic",
        "timestamp": "2025-07-03T16:39:51.646436",
        "interpretation": {
          "entity": "Student",
          "domain": "academic",
          "attributes": [
            "id: int",
            "name: str",
            "email: str"
          ],
          "extracted_attributes": [
            "id: int",
            "name: str",
            "email: str"
          ],
          "is_evolution": false,
          "request_type": "generation",
          "business_context": "Create a student management system with name and email",
          "semantic_coherence": true,
          "domain_knowledge_preserved": true,
          "interpreted_intent": "create_student_management_system",
          "domain_operations": [
            "create_entity",
            "setup_crud"
          ],
          "business_vocabulary": [
            "discente",
            "Academic",
            "aluno",
            "student",
            "Id",
            "Student",
            "estudante",
            "Learning",
            "Name",
            "Entity"
          ],
          "entity_focus": "Student",
          "swea_coordination": [
            {
              "swea_agent": "TechLeadSWEA",
              "task_type": "coordinate_system_generation",
              "payload": {
                "entity": "Student",
                "attributes": [
                  "id: int",
                  "name: str",
                  "email: str"
                ],
                "context": "Create a student management system with name and email",
                "is_evolution": false,
                "business_requirements": {
                  "domain_focus": true,
                  "semantic_coherence": true,
                  "quality_gates": true,
                  "technical_governance": true
                }
              }
            },
            {
              "swea_agent": "DatabaseSWEA",
              "task_type": "setup_database",
              "payload": {
                "entity": "Student",
                "attributes": [
                  "id: int",
                  "name: str",
                  "email: str"
                ],
                "context": "Create a student management system with name and email",
                "preserve_data": false,
                "business_rules": true
              }
            },
            {
              "swea_agent": "BackendSWEA",
              "task_type": "generate_model",
              "payload": {
                "entity": "Student",
                "attributes": [
                  "id: int",
                  "name: str",
                  "email: str"
                ],
                "context": "Create a student management system with name and email",
                "business_vocabulary": true,
                "domain_focus": true,
                "semantic_coherence": true
              }
            },
            {
              "swea_agent": "BackendSWEA",
              "task_type": "generate_api",
              "payload": {
                "entity": "Student",
                "attributes": [
                  "id: int",
                  "name: str",
                  "email: str"
                ],
                "context": "Create a student management system with name and email",
                "crud_operations": true,
                "business_vocabulary": true,
                "domain_focus": true,
                "semantic_coherence": true
              }
            },
            {
              "swea_agent": "FrontendSWEA",
              "task_type": "generate_ui",
              "payload": {
                "entity": "Student",
                "attributes": [
                  "id: int",
                  "name: str",
                  "email: str"
                ],
                "context": "Create a student management system with name and email",
                "ui_framework": "streamlit",
                "features": [
                  "crud_operations",
                  "data_visualization",
                  "user_friendly"
                ]
              }
            },
            {
              "swea_agent": "TechLeadSWEA",
              "task_type": "review_and_approve",
              "payload": {
                "entity": "Student",
                "context": "Create a student management system with name and email",
                "system_components": [
                  "database",
                  "backend",
                  "frontend"
                ],
                "phase": "phase_1_complete",
                "final_review": true
              }
            }
          ]
        },
        "current_attributes": [
          "id: int",
          "name: str",
          "email: str"
        ]
      },
      "timestamp": "2025-07-03T16:39:51.646441"
    },
    "course": {
      "entity": "course",
      "knowledge": {
        "entity": "Course",
        "context": "academic",
        "timestamp": "2025-07-03T16:37:13.818127",
        "interpretation": {
          "entity": "Course",
          "domain": "academic",
          "attributes": [
            "id: int",
            "name: str",
            "course: str"
          ],
          "extracted_attributes": [
            "id: int",
            "name: str",
            "course: str"
          ],
          "is_evolution": false,
          "request_type": "generation",
          "business_context": "Create a course entity with a name",
          "semantic_coherence": true,
          "domain_knowledge_preserved": true,
          "interpreted_intent": "create_course_management_system",
          "domain_operations": [
            "create_entity",
            "setup_crud"
          ],
          "business_vocabulary": [
            "Entity",
            "Id",
            "subject",
            "Academic",
            "course",
            "Course",
            "curso",
            "Learning",
            "disciplina",
            "mat\u00e9ria"
          ],
          "entity_focus": "Course",
          "swea_coordination": [
            {
              "swea_agent": "TechLeadSWEA",
              "task_type": "coordinate_system_generation",
              "payload": {
                "entity": "Course",
                "attributes": [
                  "id: int",
                  "name: str",
                  "course: str"
                ],
                "context": "Create a course entity with a name",
                "is_evolution": false,
                "business_requirements": {
                  "domain_focus": true,
                  "semantic_coherence": true,
                  "quality_gates": true,
                  "technical_governance": true
                }
              }
            },
            {
              "swea_agent": "DatabaseSWEA",
              "task_type": "setup_database",
              "payload": {
                "entity": "Course",
                "attributes": [
                  "id: int",
                  "name: str",
                  "course: str"
                ],
                "context": "Create a course entity with a name",
                "preserve_data": false,
                "business_rules": true
              }
            },
            {
              "swea_agent": "BackendSWEA",
              "task_type": "generate_model",
              "payload": {
                "entity": "Course",
                "attributes": [
                  "id: int",
                  "name: str",
                  "course: str"
                ],
                "context": "Create a course entity with a name",
                "business_vocabulary": true,
                "domain_focus": true,
                "semantic_coherence": true
              }
            },
            {
              "swea_agent": "BackendSWEA",
              "task_type": "generate_api",
              "payload": {
                "entity": "Course",
                "attributes": [
                  "id: int",
                  "name: str",
                  "course: str"
                ],
                "context": "Create a course entity with a name",
                "crud_operations": true,
                "business_vocabulary": true,
                "domain_focus": true,
                "semantic_coherence": true
              }
            },
            {
              "swea_agent": "FrontendSWEA",
              "task_type": "generate_ui",
              "payload": {
                "entity": "Course",
                "attributes": [
                  "id: int",
                  "name: str",
                  "course: str"
                ],
                "context": "Create a course entity with a name",
                "ui_framework": "streamlit",
                "features": [
                  "crud_operations",
                  "data_visualization",
                  "user_friendly"
                ]
              }
            },
            {
              "swea_agent": "TechLeadSWEA",
              "task_type": "review_and_approve",
              "payload": {
                "entity": "Course",
                "context": "Create a course entity with a name",
                "system_components": [
                  "database",
                  "backend",
                  "frontend"
                ],
                "phase": "phase_1_complete",
                "final_review": true
              }
            }
          ]
        },
        "current_attributes": [
          "id: int",
          "name: str",
          "course: str"
        ]
      },
      "timestamp": "2025-07-03T16:37:13.818134"
    }
  },
  "last_saved": "2025-07-03T16:39:51.647347"
}